django_lastpass_sp-0.1.6.dist-info/DESCRIPTION.rst
django_lastpass_sp-0.1.6.dist-info/METADATA
django_lastpass_sp-0.1.6.dist-info/RECORD
django_lastpass_sp-0.1.6.dist-info/WHEEL
django_lastpass_sp-0.1.6.dist-info/metadata.json
django_lastpass_sp-0.1.6.dist-info/pbr.json
django_lastpass_sp-0.1.6.dist-info/top_level.txt
lpsp/__init__.py
lpsp/_version.py
lpsp/auth_backend.py
lpsp/models.py
lpsp/settings.py
lpsp/urls.py
lpsp/views.py
