Metadata-Version: 2.0
Name: django-lastpass-sp
Version: 0.1.6
Summary: Django LastPass SAML authenticator
Home-page: https://github.com/codetry/lpsp/
Author: Ferrix Hovi
Author-email: ferrix@codetry.fi
License: MIT License
Platform: UNKNOWN
Classifier: Environment :: Web Environment
Classifier: Framework :: Django
Classifier: Framework :: Django :: 1.8
Classifier: Intended Audience :: Developers
Classifier: Operating System :: OS Independent
Classifier: Programming Language :: Python
Classifier: License :: OSI Approved :: MIT License
Classifier: Topic :: Internet :: WWW/HTTP
Classifier: Topic :: Internet :: WWW/HTTP :: Dynamic Content
Requires-Dist: Django (>=1.8.2)
Requires-Dist: django-saml-service-provider (==1.0.2)
